claude_everything/__init__.py
claude_everything/graph.py
claude_everything/model.py
claude_everything/prompts.py
claude_everything/sub_agent.py
claude_everything/tools.py
claude_everything-0.0.1.dist-info/licenses/LICENSE
claude_everything-0.0.1.dist-info/METADATA
claude_everything-0.0.1.dist-info/WHEEL
claude_everything-0.0.1.dist-info/top_level.txt
claude_everything-0.0.1.dist-info/RECORD
