Metadata-Version: 2.4
Name: claude-everything
Version: 0.0.1
Summary: General purpose Claude agent with sub-agent spawning and todo list capabilities using LangGraph.
License: MIT
Requires-Python: <4.0,>=3.11
License-File: LICENSE
Requires-Dist: langgraph>=0.2.6
Requires-Dist: langchain-anthropic>=0.1.23
Requires-Dist: langchain>=0.2.14
Dynamic: license-file
